async_fsm/__init__.py
async_fsm/conf.py
async_fsm/fsm.py
async_fsm/messages.py
async_fsm-0.1.0.dist-info/AUTHORS.rst
async_fsm-0.1.0.dist-info/LICENSE
async_fsm-0.1.0.dist-info/METADATA
async_fsm-0.1.0.dist-info/WHEEL
async_fsm-0.1.0.dist-info/top_level.txt
async_fsm-0.1.0.dist-info/RECORD
