Metadata-Version: 2.1
Name: async-fsm
Version: 0.1.0
Summary: A finite state machine implementation with asyncio
Home-page: https://github.com/benthomasson/async_fsm
Author: Ben Thomasson
Author-email: bthomass@redhat.com
License: Apache Software License 2.0
Keywords: async_fsm
Platform: UNKNOWN
Classifier: Development Status :: 2 - Pre-Alpha
Classifier: Intended Audience :: Developers
Classifier: License :: OSI Approved :: Apache Software License
Classifier: Natural Language :: English
Classifier: Programming Language :: Python :: 2
Classifier: Programming Language :: Python :: 2.7
Classifier: Programming Language :: Python :: 3
Classifier: Programming Language :: Python :: 3.4
Classifier: Programming Language :: Python :: 3.5
Classifier: Programming Language :: Python :: 3.6
Classifier: Programming Language :: Python :: 3.7
